kdecolepy/__init__.py
kdecolepy/api_constants.py
kdecolepy/kdecole.py
kdecolepy-0.1.2.dist-info/METADATA
kdecolepy-0.1.2.dist-info/WHEEL
kdecolepy-0.1.2.dist-info/licenses/LICENSE
kdecolepy-0.1.2.dist-info/RECORD
